varoon/__init__.py
varoon/main.py
varoon-0.3.0.dist-info/LICENSE
varoon-0.3.0.dist-info/METADATA
varoon-0.3.0.dist-info/WHEEL
varoon-0.3.0.dist-info/entry_points.txt
varoon-0.3.0.dist-info/top_level.txt
varoon-0.3.0.dist-info/RECORD
