Metadata-Version: 2.1
Name: varoon
Version: 0.3.0
Summary: A tool for checking reflected parameters in URLs
Home-page: https://github.com/R0X4R/varoon
Author: Eshan Singh
Author-email: r0x4r@yahoo.com
License: UNKNOWN
Platform: UNKNOWN
Classifier: Programming Language :: Python :: 3
Classifier: License :: OSI Approved :: MIT License
Classifier: Operating System :: OS Independent
Requires-Python: >=3.6
License-File: LICENSE
Requires-Dist: aiohttp (>=3.8.1)
